MINDGROVE/ram_16x4.v
`timescale 1ns / 1ps
////////////////////////////////////////////////////////////////////////////////
// Company: 
// Engineer:
//
// Create Date:    09:29:02 11/11/25
// Design Name:    
// Module Name:    ram_16x4
// Project Name:   
// Target Device:  
// Tool versions:  
// Description:
//
// Dependencies:
// 
// Revision:
// Revision 0.01 - File Created
// Additional Comments:
// 
////////////////////////////////////////////////////////////////////////////////
// =========================================================
// 16x4 Synchronous RAM with Active-Low Reset & Chip Select
// =========================================================
// =========================================================
// Synchronous 16x4 RAM (single-port)
// Compatible with Xilinx XST / Vivado synthesis
// =========================================================
module ram_16x4_sync(
    input clk,
    input reset_n,
    input [3:0] addr,
    input [3:0] datain,
    input csn,               // 0 = memory in use
    input rwn,               // 1 = read, 0 = write
    output reg [3:0] dataout
);
    reg [3:0] memory [0:15];
    integer i;
    
    // Initialize memory
    initial begin
        for (i = 0; i < 16; i = i + 1) begin
            memory[i] = 4'b0000;
        end
    end
    
    // Synchronous read/write operation
    always @(posedge clk or negedge reset_n) begin
        if (!reset_n) begin
            dataout <= 4'b0000;
        end else begin
            if (!csn) begin
                if (!rwn) begin
                    // Write operation
                    memory[addr] <= datain;
                end else begin
                    // Read operation
                    dataout <= memory[addr];
                end
            end
        end
    end
endmodule

MINDGROVE/xor_gate.v
`timescale 1ns / 1ps
////////////////////////////////////////////////////////////////////////////////
// Company: 
// Engineer:
//
// Create Date:    09:21:58 11/11/25
// Design Name:    
// Module Name:    xor_gate
// Project Name:   
// Target Device:  
// Tool versions:  
// Description:
//
// Dependencies:
// 
// Revision:
// Revision 0.01 - File Created
// Additional Comments:
// 
////////////////////////////////////////////////////////////////////////////////
module xor_gate(
    input a,
    input b,
    output c
);
    // Behavioral description without using built-in xor
    assign c = (a & ~b) | (~a & b);
endmodule

MINDGROVE/full_adder_1bit.v
`timescale 1ns / 1ps
////////////////////////////////////////////////////////////////////////////////
// Company: 
// Engineer:
//
// Create Date:    09:44:27 11/11/25
// Design Name:    
// Module Name:    full_adder_1bit
// Project Name:   
// Target Device:  
// Tool versions:  
// Description:
//
// Dependencies:
// 
// Revision:
// Revision 0.01 - File Created
// Additional Comments:
// 
////////////////////////////////////////////////////////////////////////////////
module full_adder_1bit(
    input a,
    input b,
    input cin,
    output sum,
    output cout
);
    wire xor_ab;
    wire and1, and2;
    
    // Sum = a XOR b XOR cin (using XOR gate from Step 1)
    xor_gate xg1(.a(a), .b(b), .c(xor_ab));
    xor_gate xg2(.a(xor_ab), .b(cin), .c(sum));
    
    // Carry out = (a AND b) OR (cin AND (a XOR b))
    assign and1 = a & b;
    assign and2 = cin & xor_ab;
    assign cout = and1 | and2;
endmodule

MINDGROVE/adder_4bit.v
`timescale 1ns / 1ps
////////////////////////////////////////////////////////////////////////////////
// Company: 
// Engineer:
//
// Create Date:    09:24:20 11/11/25
// Design Name:    
// Module Name:    adder_4bit
// Project Name:   
// Target Device:  
// Tool versions:  
// Description:
//
// Dependencies:
// 
// Revision:
// Revision 0.01 - File Created
// Additional Comments:
// 
////////////////////////////////////////////////////////////////////////////////
module adder_4bit(
    input [3:0] a,
    input [3:0] b,
    input cin,
    output [3:0] sum,
    output cout
);
    wire c1, c2, c3;
    
    full_adder_1bit fa0(.a(a[0]), .b(b[0]), .cin(cin), .sum(sum[0]), .cout(c1));
    full_adder_1bit fa1(.a(a[1]), .b(b[1]), .cin(c1), .sum(sum[1]), .cout(c2));
    full_adder_1bit fa2(.a(a[2]), .b(b[2]), .cin(c2), .sum(sum[2]), .cout(c3));
    full_adder_1bit fa3(.a(a[3]), .b(b[3]), .cin(c3), .sum(sum[3]), .cout(cout));
endmodule

MINDGROVE/alu_4bit.v
`timescale 1ns / 1ps
////////////////////////////////////////////////////////////////////////////////
// Company: 
// Engineer:
//
// Create Date:    09:25:01 11/11/25
// Design Name:    
// Module Name:    alu_4bit
// Project Name:   
// Target Device:  
// Tool versions:  
// Description:
//
// Dependencies:
// 
// Revision:
// Revision 0.01 - File Created
// Additional Comments:
// 
////////////////////////////////////////////////////////////////////////////////
module alu_4bit(
    input [2:0] sel,      // S2, S1, S0
    input [3:0] a,
    input [3:0] b,
    input cin,
    output reg [3:0] f,
    output reg cout
);
    wire [3:0] adder_out;
    wire adder_cout;
    wire [3:0] b_modified;
    wire cin_modified;
    wire [3:0] xor_result;
    
    // Generate XOR result
    xor_gate xg0(.a(a[0]), .b(b[0]), .c(xor_result[0]));
    xor_gate xg1(.a(a[1]), .b(b[1]), .c(xor_result[1]));
    xor_gate xg2(.a(a[2]), .b(b[2]), .c(xor_result[2]));
    xor_gate xg3(.a(a[3]), .b(b[3]), .c(xor_result[3]));
    
    // Modify b and cin based on operation
    assign b_modified = (sel[2:1] == 2'b00) ? 
                        ((sel[0] == 1'b0 && cin == 1'b0) ? 4'b0000 :  // Transfer a
                         (sel[0] == 1'b0 && cin == 1'b1) ? 4'b0000 :  // Increment
                         (sel[0] == 1'b1 && cin == 1'b0) ? b :         // Add
                         b) :                                           // Add with carry
                        (sel[2:0] == 3'b010 || sel[2:0] == 3'b011) ? ~b :  // Subtract
                        (sel[2:0] == 3'b110) ? 4'b1111 :               // Decrement
                        (sel[2:0] == 3'b111) ? 4'b1111 :               // Transfer
                        b;
    
    assign cin_modified = (sel[2:1] == 2'b00) ? cin :
                          (sel[2:0] == 3'b101 || sel[2:0] == 3'b110) ? 1'b1 :
                          1'b0;
    
    // Instantiate adder
    adder_4bit adder(.a(a), .b(b_modified), .cin(cin_modified), 
                     .sum(adder_out), .cout(adder_cout));
    
    // ALU operation select
    always @(*) begin
        case(sel)
            3'b000: begin f = adder_out; cout = adder_cout; end  // Increment / Transfer
            3'b001: begin f = adder_out; cout = adder_cout; end  // Add / Add with carry
            3'b010: begin f = adder_out; cout = adder_cout; end  // Subtract
            3'b011: begin f = adder_out; cout = adder_cout; end  // Subtract with borrow
            3'b100: begin f = a & b; cout = 1'b0; end            // AND
            3'b101: begin f = a | b; cout = 1'b0; end            // OR
            3'b110: begin f = xor_result; cout = 1'b0; end       // XOR
            3'b111: begin f = ~a; cout = 1'b0; end               // NOT
            default: begin f = 4'b0000; cout = 1'b0; end
        endcase
    end
endmodule

MINDGROVE/registered_alu.v
`timescale 1ns / 1ps
////////////////////////////////////////////////////////////////////////////////
// Company: 
// Engineer:
//
// Create Date:    09:25:29 11/11/25
// Design Name:    
// Module Name:    registered_alu
// Project Name:   
// Target Device:  
// Tool versions:  
// Description:
//
// Dependencies:
// 
// Revision:
// Revision 0.01 - File Created
// Additional Comments:
// 
////////////////////////////////////////////////////////////////////////////////
module registered_alu(
    input clk,
    input reset_n,
    input [2:0] sel,
    input [3:0] a,
    input [3:0] b,
    input cin,
    output reg [3:0] f,
    output reg cout
);
    wire [3:0] alu_f;
    wire alu_cout;
    
    // Instantiate ALU
    alu_4bit alu(.sel(sel), .a(a), .b(b), .cin(cin), .f(alu_f), .cout(alu_cout));
    
    // Register outputs
    always @(posedge clk or negedge reset_n) begin
        if (!reset_n) begin
            f <= 4'b0000;
            cout <= 1'b0;
        end else begin
            f <= alu_f;
            cout <= alu_cout;
        end
    end
endmodule

MINDGROVE/instruction_decoder.v
`timescale 1ns / 1ps
////////////////////////////////////////////////////////////////////////////////
// Company: 
// Engineer:
//
// Create Date:    09:28:17 11/11/25
// Design Name:    
// Module Name:    instruction_decoder
// Project Name:   
// Target Device:  
// Tool versions:  
// Description:
//
// Dependencies:
// 
// Revision:
// Revision 0.01 - File Created
// Additional Comments:
// 
////////////////////////////////////////////////////////////////////////////////
module instruction_decoder(
    input clk,
    input reset_n,
    input [10:0] instruction,    // [opcode(3)][op1(4)][op2(4)]
    output reg [2:0] alu_sel,
    output reg [3:0] addr,
    output reg [3:0] operand,
    output reg csn,              // Chip select for RAM
    output reg rwn,              // Read/Write for RAM
    output reg alu_enable,
    output reg [1:0] state
);
    // State definitions
    localparam INIT = 2'b00;
    localparam FETCH = 2'b01;
    localparam EXECUTE = 2'b10;
    localparam STORE = 2'b11;
    
    // Instruction fields
    wire [2:0] opcode;
    wire [3:0] op1;  // Destination memory address
    wire [3:0] op2;  // Source (constant/immediate value)
    
    assign opcode = instruction[10:8];
    assign op1 = instruction[7:4];
    assign op2 = instruction[3:0];
    
    // State machine with asynchronous reset
    always @(posedge clk or negedge reset_n) begin
        if (!reset_n) begin
            state <= INIT;
            alu_sel <= 3'b000;
            addr <= 4'b0000;
            operand <= 4'b0000;
            csn <= 1'b1;          // RAM not selected
            rwn <= 1'b1;          // Read mode
            alu_enable <= 1'b0;
        end else begin
            case(state)
                INIT: begin
                    state <= FETCH;
                    csn <= 1'b1;
                    rwn <= 1'b1;
                    alu_enable <= 1'b0;
                end
                
                FETCH: begin
                    // Fetch data from memory location specified by op1
                    state <= EXECUTE;
                    addr <= op1;
                    csn <= 1'b0;      // Select RAM
                    rwn <= 1'b1;      // Read mode
                    alu_enable <= 1'b0;
                end
                
                EXECUTE: begin
                    // Execute instruction using ALU
                    state <= STORE;
                    operand <= op2;
                    csn <= 1'b1;      // Deselect RAM during execute
                    alu_enable <= 1'b1;
                    
                    // Decode opcode and set ALU control signals
                    case(opcode)
                        3'b000: alu_sel <= 3'b000;  // STO (Transfer) - f = a (with b=0000, cin=0)
                        3'b001: alu_sel <= 3'b001;  // ADD - f = a + b
                        3'b010: alu_sel <= 3'b011;  // SUB - f = a + ~b + 1
                        3'b011: alu_sel <= 3'b110;  // AND - f = a & b
                        3'b100: alu_sel <= 3'b100;  // OR - f = a | b
                        3'b101: alu_sel <= 3'b101;  // XOR - f = a ^ b
                        3'b110: alu_sel <= 3'b111;  // NOT - f = ~a
                        default: alu_sel <= 3'b000;
                    endcase
                end
                
                STORE: begin
                    // Store result back to memory location op1
                    state <= FETCH;
                    addr <= op1;
                    csn <= 1'b0;      // Select RAM
                    rwn <= 1'b0;      // Write mode
                    alu_enable <= 1'b0;
                end
                
                default: state <= INIT;
            endcase
        end
    end
endmodule

MINDGROVE/processor_4bit.v
`timescale 1ns / 1ps
////////////////////////////////////////////////////////////////////////////////
// Company: 
// Engineer:
//
// Create Date:    09:30:14 11/11/25
// Design Name:    
// Module Name:    processor_4bit
// Project Name:   
// Target Device:  
// Tool versions:  
// Description:
//
// Dependencies:
// 
// Revision:
// Revision 0.01 - File Created
// Additional Comments:
// 
////////////////////////////////////////////////////////////////////////////////
module processor_4bit(
    input clk,
    input reset_n,
    input [10:0] instruction,
    output [3:0] result,
    output [3:0] mem_out,      // For debugging
    output [1:0] current_state
);
    // Internal signals
    wire [2:0] alu_sel;
    wire [3:0] addr;
    wire [3:0] operand;
    wire csn, rwn, alu_enable;
    wire [3:0] mem_data;
    wire [3:0] alu_result;
    wire alu_cout;
    
    // Instantiate Instruction Decoder (Step 5)
    instruction_decoder decoder(
        .clk(clk),
        .reset_n(reset_n),
        .instruction(instruction),
        .alu_sel(alu_sel),
        .addr(addr),
        .operand(operand),
        .csn(csn),
        .rwn(rwn),
        .alu_enable(alu_enable),
        .state(current_state)
    );
    
    // Instantiate Registered ALU (Step 4)
    registered_alu alu(
        .clk(clk),
        .reset_n(reset_n),
        .sel(alu_sel),
        .a(mem_data),        // Data from memory
        .b(operand),         // Immediate operand
        .cin(1'b0),
        .f(alu_result),
        .cout(alu_cout)
    );
    
    // Instantiate Synchronous RAM (Step 8)
    ram_16x4_sync ram(
        .clk(clk),
        .reset_n(reset_n),
        .addr(addr),
        .datain(alu_result),
        .csn(csn),
        .rwn(rwn),
        .dataout(mem_data)
    );
    
    // Output assignments
    assign result = alu_result;
    assign mem_out = mem_data;
endmodule

MINDGROVE/processor_4bit_tb.v
`timescale 1ns / 1ps

////////////////////////////////////////////////////////////////////////////////
// Company: 
// Engineer:
//
// Create Date:   09:41:12 11/11/2025
// Design Name:   processor_4bit
// Module Name:   processor_4bit_tb.v
// Project Name:  mindgrove
// Target Device:  
// Tool versions:  
// Description: 
//
// Verilog Test Fixture created by ISE for module: processor_4bit
//
// Dependencies:
// 
// Revision:
// Revision 0.01 - File Created
// Additional Comments:
// 
////////////////////////////////////////////////////////////////////////////////

module processor_4bit_tb;
    reg clk, reset_n;
    reg [10:0] instruction;
    wire [3:0] result;
    wire [3:0] mem_out;
    wire [1:0] current_state;
    
    // Instantiate Processor
    processor_4bit uut(
        .clk(clk),
        .reset_n(reset_n),
        .instruction(instruction),
        .result(result),
        .mem_out(mem_out),
        .current_state(current_state)
    );
    
    // Clock generation
    initial begin
        clk = 0;
        forever #5 clk = ~clk;
    end

    // --- VCD DUMP FILE CONFIGURATION ---
    initial begin
        $dumpfile("processor_4bit_tb.vcd");   // Name of the VCD output file
        $dumpvars(0, processor_4bit_tb);      // Dump all signals in this module
    end
    
    // State display
    function [63:0] state_name;
        input [1:0] s;
        begin
            case(s)
                2'b00: state_name = "INIT   ";
                2'b01: state_name = "FETCH  ";
                2'b10: state_name = "EXECUTE";
                2'b11: state_name = "STORE  ";
            endcase
        end
    endfunction
    
    initial begin
        $display("============================================");
        $display("STEP 7: Testing Complete 4-bit Processor");
        $display("============================================");
        $display("\nInstruction Format: [Opcode(3)][Addr(4)][Immediate(4)]");
        $display("Opcodes: STO=000, ADD=001, SUB=010, AND=011, OR=100, XOR=101, NOT=110\n");
        
        // Reset
        reset_n = 0;
        instruction = 11'b0;
        #20;
        reset_n = 1;
        #10;
        $display("Processor initialized\n");
        
        // Assembly Program
        $display("Executing Sample Assembly Program:\n");
        
        // 1. STO [0], 5
        $display("1. STO [0], 5  - Store 5 at address 0");
        instruction = 11'b000_0000_0101;
        #30;
        $display("   Result: Memory[0] = %d\n", result);
        
        // 2. ADD [0], 3
        $display("2. ADD [0], 3  - Add 3 to address 0 (5+3=8)");
        instruction = 11'b001_0000_0011;
        #30;
        $display("   Result: Memory[0] = %d\n", result);
        
        // 3. SUB [0], 2
        $display("3. SUB [0], 2  - Subtract 2 from address 0 (8-2=6)");
        instruction = 11'b010_0000_0010;
        #30;
        $display("   Result: Memory[0] = %d\n", result);
        
        // 4. STO [1], 12
        $display("4. STO [1], 12 - Store 12 at address 1");
        instruction = 11'b000_0001_1100;
        #30;
        $display("   Result: Memory[1] = %d\n", result);
        
        // 5. AND [1], 7
        $display("5. AND [1], 7  - AND address 1 with 7 (12&7=4)");
        instruction = 11'b011_0001_0111;
        #30;
        $display("   Result: Memory[1] = %d\n", result);
        
        // 6. OR [1], 8
        $display("6. OR [1], 8   - OR address 1 with 8 (4|8=12)");
        instruction = 11'b100_0001_1000;
        #30;
        $display("   Result: Memory[1] = %d\n", result);
        
        // 7. XOR [1], 15
        $display("7. XOR [1], 15 - XOR address 1 with 15 (12^15=3)");
        instruction = 11'b101_0001_1111;
        #30;
        $display("   Result: Memory[1] = %d\n", result);
        
        // 8. NOT [1], 0
        $display("8. NOT [1], 0  - NOT value at address 1 (~3=12)");
        instruction = 11'b110_0001_0000;
        #30;
        $display("   Result: Memory[1] = %d\n", result);
        
        // Verify final values
        $display("\n--- Final Memory Check ---");
        instruction = 11'b001_0000_0000;  // Read address 0
        #30;
        $display("Memory[0] = %d (expected 6)", result);
        
        instruction = 11'b001_0001_0000;  // Read address 1
        #30;
        $display("Memory[1] = %d (expected 12)", result);
        
        $display("\n============================================");
        $display("Complete Processor Test PASSED!");
        $display("============================================\n");
        
        #50;
        $finish;
    end
    
    // Monitor state transitions
    always @(posedge clk) begin
        if (current_state != 2'b00)  // Skip INIT state
            $display("   [%0t] State: %s", $time, state_name(current_state));
    end
endmodule

MINDGROVE/processor_4bit_tb.vcd
$date
	Tue Nov 11 16:53:29 2025
$end
$version
	ModelSim Version 6.4a
$end
$timescale
	1ps
$end
$scope module processor_4bit_tb $end
$var reg 1 ! clk $end
$var reg 1 " reset_n $end
$var reg 11 # instruction [10:0] $end
$var wire 1 $ result [3] $end
$var wire 1 % result [2] $end
$var wire 1 & result [1] $end
$var wire 1 ' result [0] $end
$var wire 1 ( mem_out [3] $end
$var wire 1 ) mem_out [2] $end
$var wire 1 * mem_out [1] $end
$var wire 1 + mem_out [0] $end
$var wire 1 , current_state [1] $end
$var wire 1 - current_state [0] $end
$scope function state_name $end
$var reg 64 . state_name [63:0] $end
$var reg 2 / s [1:0] $end
$upscope $end
$scope module uut $end
$var wire 1 0 clk $end
$var wire 1 1 reset_n $end
$var wire 1 2 instruction [10] $end
$var wire 1 3 instruction [9] $end
$var wire 1 4 instruction [8] $end
$var wire 1 5 instruction [7] $end
$var wire 1 6 instruction [6] $end
$var wire 1 7 instruction [5] $end
$var wire 1 8 instruction [4] $end
$var wire 1 9 instruction [3] $end
$var wire 1 : instruction [2] $end
$var wire 1 ; instruction [1] $end
$var wire 1 < instruction [0] $end
$var wire 1 $ result [3] $end
$var wire 1 % result [2] $end
$var wire 1 & result [1] $end
$var wire 1 ' result [0] $end
$var wire 1 ( mem_out [3] $end
$var wire 1 ) mem_out [2] $end
$var wire 1 * mem_out [1] $end
$var wire 1 + mem_out [0] $end
$var wire 1 , current_state [1] $end
$var wire 1 - current_state [0] $end
$var wire 1 = alu_sel [2] $end
$var wire 1 > alu_sel [1] $end
$var wire 1 ? alu_sel [0] $end
$var wire 1 @ addr [3] $end
$var wire 1 A addr [2] $end
$var wire 1 B addr [1] $end
$var wire 1 C addr [0] $end
$var wire 1 D operand [3] $end
$var wire 1 E operand [2] $end
$var wire 1 F operand [1] $end
$var wire 1 G operand [0] $end
$var wire 1 H csn $end
$var wire 1 I rwn $end
$var wire 1 J alu_enable $end
$var wire 1 K mem_data [3] $end
$var wire 1 L mem_data [2] $end
$var wire 1 M mem_data [1] $end
$var wire 1 N mem_data [0] $end
$var wire 1 O alu_result [3] $end
$var wire 1 P alu_result [2] $end
$var wire 1 Q alu_result [1] $end
$var wire 1 R alu_result [0] $end
$var wire 1 S alu_cout $end
$scope module decoder $end
$var parameter 2 T INIT $end
$var parameter 2 U FETCH $end
$var parameter 2 V EXECUTE $end
$var parameter 2 W STORE $end
$var wire 1 0 clk $end
$var wire 1 1 reset_n $end
$var wire 1 2 instruction [10] $end
$var wire 1 3 instruction [9] $end
$var wire 1 4 instruction [8] $end
$var wire 1 5 instruction [7] $end
$var wire 1 6 instruction [6] $end
$var wire 1 7 instruction [5] $end
$var wire 1 8 instruction [4] $end
$var wire 1 9 instruction [3] $end
$var wire 1 : instruction [2] $end
$var wire 1 ; instruction [1] $end
$var wire 1 < instruction [0] $end
$var reg 3 X alu_sel [2:0] $end
$var reg 4 Y addr [3:0] $end
$var reg 4 Z operand [3:0] $end
$var reg 1 [ csn $end
$var reg 1 \ rwn $end
$var reg 1 ] alu_enable $end
$var reg 2 ^ state [1:0] $end
$var wire 1 _ opcode [2] $end
$var wire 1 ` opcode [1] $end
$var wire 1 a opcode [0] $end
$var wire 1 b op1 [3] $end
$var wire 1 c op1 [2] $end
$var wire 1 d op1 [1] $end
$var wire 1 e op1 [0] $end
$var wire 1 f op2 [3] $end
$var wire 1 g op2 [2] $end
$var wire 1 h op2 [1] $end
$var wire 1 i op2 [0] $end
$upscope $end
$scope module alu $end
$var wire 1 0 clk $end
$var wire 1 1 reset_n $end
$var wire 1 = sel [2] $end
$var wire 1 > sel [1] $end
$var wire 1 ? sel [0] $end
$var wire 1 K a [3] $end
$var wire 1 L a [2] $end
$var wire 1 M a [1] $end
$var wire 1 N a [0] $end
$var wire 1 D b [3] $end
$var wire 1 E b [2] $end
$var wire 1 F b [1] $end
$var wire 1 G b [0] $end
$var wire 1 j cin $end
$var reg 4 k f [3:0] $end
$var reg 1 l cout $end
$var wire 1 m alu_f [3] $end
$var wire 1 n alu_f [2] $end
$var wire 1 o alu_f [1] $end
$var wire 1 p alu_f [0] $end
$var wire 1 q alu_cout $end
$scope module alu $end
$var wire 1 = sel [2] $end
$var wire 1 > sel [1] $end
$var wire 1 ? sel [0] $end
$var wire 1 K a [3] $end
$var wire 1 L a [2] $end
$var wire 1 M a [1] $end
$var wire 1 N a [0] $end
$var wire 1 D b [3] $end
$var wire 1 E b [2] $end
$var wire 1 F b [1] $end
$var wire 1 G b [0] $end
$var wire 1 j cin $end
$var reg 4 r f [3:0] $end
$var reg 1 s cout $end
$var wire 1 t adder_out [3] $end
$var wire 1 u adder_out [2] $end
$var wire 1 v adder_out [1] $end
$var wire 1 w adder_out [0] $end
$var wire 1 x adder_cout $end
$var wire 1 y b_modified [3] $end
$var wire 1 z b_modified [2] $end
$var wire 1 { b_modified [1] $end
$var wire 1 | b_modified [0] $end
$var wire 1 } cin_modified $end
$var wire 1 ~ xor_result [3] $end
$var wire 1 !! xor_result [2] $end
$var wire 1 "! xor_result [1] $end
$var wire 1 #! xor_result [0] $end
$scope module xg0 $end
$var wire 1 N a $end
$var wire 1 G b $end
$var wire 1 #! c $end
$upscope $end
$scope module xg1 $end
$var wire 1 M a $end
$var wire 1 F b $end
$var wire 1 "! c $end
$upscope $end
$scope module xg2 $end
$var wire 1 L a $end
$var wire 1 E b $end
$var wire 1 !! c $end
$upscope $end
$scope module xg3 $end
$var wire 1 K a $end
$var wire 1 D b $end
$var wire 1 ~ c $end
$upscope $end
$scope module adder $end
$var wire 1 K a [3] $end
$var wire 1 L a [2] $end
$var wire 1 M a [1] $end
$var wire 1 N a [0] $end
$var wire 1 y b [3] $end
$var wire 1 z b [2] $end
$var wire 1 { b [1] $end
$var wire 1 | b [0] $end
$var wire 1 } cin $end
$var wire 1 t sum [3] $end
$var wire 1 u sum [2] $end
$var wire 1 v sum [1] $end
$var wire 1 w sum [0] $end
$var wire 1 x cout $end
$var wire 1 $! c1 $end
$var wire 1 %! c2 $end
$var wire 1 &! c3 $end
$scope module fa0 $end
$var wire 1 N a $end
$var wire 1 | b $end
$var wire 1 } cin $end
$var wire 1 w sum $end
$var wire 1 $! cout $end
$var wire 1 '! xor_ab $end
$var wire 1 (! and1 $end
$var wire 1 )! and2 $end
$scope module xg1 $end
$var wire 1 N a $end
$var wire 1 | b $end
$var wire 1 '! c $end
$upscope $end
$scope module xg2 $end
$var wire 1 '! a $end
$var wire 1 } b $end
$var wire 1 w c $end
$upscope $end
$upscope $end
$scope module fa1 $end
$var wire 1 M a $end
$var wire 1 { b $end
$var wire 1 $! cin $end
$var wire 1 v sum $end
$var wire 1 %! cout $end
$var wire 1 *! xor_ab $end
$var wire 1 +! and1 $end
$var wire 1 ,! and2 $end
$scope module xg1 $end
$var wire 1 M a $end
$var wire 1 { b $end
$var wire 1 *! c $end
$upscope $end
$scope module xg2 $end
$var wire 1 *! a $end
$var wire 1 $! b $end
$var wire 1 v c $end
$upscope $end
$upscope $end
$scope module fa2 $end
$var wire 1 L a $end
$var wire 1 z b $end
$var wire 1 %! cin $end
$var wire 1 u sum $end
$var wire 1 &! cout $end
$var wire 1 -! xor_ab $end
$var wire 1 .! and1 $end
$var wire 1 /! and2 $end
$scope module xg1 $end
$var wire 1 L a $end
$var wire 1 z b $end
$var wire 1 -! c $end
$upscope $end
$scope module xg2 $end
$var wire 1 -! a $end
$var wire 1 %! b $end
$var wire 1 u c $end
$upscope $end
$upscope $end
$scope module fa3 $end
$var wire 1 K a $end
$var wire 1 y b $end
$var wire 1 &! cin $end
$var wire 1 t sum $end
$var wire 1 x cout $end
$var wire 1 0! xor_ab $end
$var wire 1 1! and1 $end
$var wire 1 2! and2 $end
$scope module xg1 $end
$var wire 1 K a $end
$var wire 1 y b $end
$var wire 1 0! c $end
$upscope $end
$scope module xg2 $end
$var wire 1 0! a $end
$var wire 1 &! b $end
$var wire 1 t c $end
$upscope $end
$upscope $end
$upscope $end
$upscope $end
$upscope $end
$scope module ram $end
$var wire 1 0 clk $end
$var wire 1 1 reset_n $end
$var wire 1 @ addr [3] $end
$var wire 1 A addr [2] $end
$var wire 1 B addr [1] $end
$var wire 1 C addr [0] $end
$var wire 1 O datain [3] $end
$var wire 1 P datain [2] $end
$var wire 1 Q datain [1] $end
$var wire 1 R datain [0] $end
$var wire 1 H csn $end
$var wire 1 I rwn $end
$var reg 4 3! dataout [3:0] $end
$var integer 32 4! i $end
$upscope $end
$upscope $end
$upscope $end
$enddefinitions $end
#0
$dumpvars
b0 T
b1 U
b10 V
b11 W
0!
0"
b0 #
b0 X
b0 Y
b0 Z
1[
1\
0]
b0 ^
b0 k
0l
b0 r
0s
b0 3!
b10000 4!
bx .
bx /
0'
0&
0%
0$
0+
0*
0)
0(
0-
0,
0?
0>
0=
0C
0B
0A
0@
0G
0F
0E
0D
1H
1I
0J
0N
0M
0L
0K
0R
0Q
0P
0O
0S
0a
0`
0_
0e
0d
0c
0b
0i
0h
0g
0f
0p
0o
0n
0m
0q
0w
0v
0u
0t
0x
0|
0{
0z
0y
0}
0#!
0"!
0!!
0~
0$!
0%!
0&!
0'!
0(!
0)!
0*!
0+!
0,!
0-!
0.!
0/!
00!
01!
02!
0<
0;
0:
09
08
07
06
05
04
03
02
01
00
0j
$end
#5000
1!
10
#10000
0!
00
#15000
1!
10
#20000
1"
0!
00
11
#25000
1!
10
b1 ^
1-
#30000
b101 #
0!
00
1<
1:
1i
1g
#35000
1!
b1 /
b1000110010001010101010001000011010010000010000000100000 .
10
b10 ^
0[
0H
0-
1,
#40000
0!
00
#45000
1!
b10 /
b1000101010110000100010101000011010101010101010001000101 .
10
b11 ^
b101 Z
1[
1]
1J
1H
1G
1E
1-
1!!
1#!
#50000
0!
00
#55000
1!
b11 /
b1010011010101000100111101010010010001010010000000100000 .
10
b1 ^
0[
0\
0]
0J
0I
0H
0,
#60000
b100000011 #
0!
00
1;
0:
14
1a
1h
0g
#65000
1!
b1 /
b1000110010001010101010001000011010010000010000000100000 .
10
b10 ^
1\
1I
0-
1,
#70000
0!
00
#75000
1!
b10 /
b1000101010110000100010101000011010101010101010001000101 .
10
b11 ^
b11 Z
1[
1]
b1 X
1?
1J
1H
1F
0E
1-
0!!
1"!
1|
1{
1*!
1'!
1w
1v
b11 r
1p
1o
#80000
0!
00
#85000
1!
b11 /
b1010011010101000100111101010010010001010010000000100000 .
10
b1 ^
0[
0\
0]
b11 k
1R
1Q
0J
0I
0H
0,
1'
1&
#90000
b1000000010 #
0!
00
0<
04
13
0a
1`
0i
#95000
1!
b1 /
b1000110010001010101010001000011010010000010000000100000 .
10
b10 ^
1\
1I
0-
1,
#100000
0!
00
#105000
1!
b10 /
b1000101010110000100010101000011010101010101010001000101 .
10
b11 ^
b10 Z
1[
1]
b11 X
b11 3!
1N
1M
1>
1J
1H
0G
1-
0{
1z
1y
0"!
0*!
1+!
0'!
1(!
1+
1*
1$!
0w
1%!
0v
10!
1-!
1*!
0+!
b0 r
0%!
1t
1/!
1,!
0p
0o
b1000 r
1%!
1&!
1u
0/!
1m
b1100 r
0&!
0t
12!
0u
1/!
1n
b0 r
1&!
1x
1t
02!
0n
0m
b1000 r
1s
0x
0t
12!
1q
1m
b0 r
0s
1x
0q
0m
1s
1q
#110000
0!
00
#115000
1!
b11 /
b1010011010101000100111101010010010001010010000000100000 .
10
b1 ^
0[
0\
0]
b0 k
1l
1S
0R
0Q
0J
0I
0H
0,
0'
0&
#120000
b11100 #
0!
00
0;
1:
19
18
03
0`
1e
0h
1g
1f
#125000
1!
b1 /
b1000110010001010101010001000011010010000010000000100000 .
10
b10 ^
b1 Y
1\
1I
1C
0-
1,
#130000
0!
00
#135000
1!
b10 /
b1000101010110000100010101000011010101010101010001000101 .
10
b11 ^
b1100 Z
1[
1]
b0 X
b0 3!
0N
0M
0?
0>
1J
1H
0F
1E
1D
1-
1~
1!!
0|
0z
0y
0*!
0#!
1'!
0(!
0+
0*
0$!
1w
1v
0,!
00!
0-!
0'!
b11 r
0w
1u
0/!
1t
02!
0%!
0v
1p
1o
b1100 r
0u
0x
0&!
0p
0o
1n
1m
b1000 r
0s
0t
0q
0n
b0 r
0m
#140000
0!
00
#145000
1!
b11 /
b1010011010101000100111101010010010001010010000000100000 .
10
b1 ^
0[
0\
0]
0l
0S
0J
0I
0H
0,
#150000
b1100010111 #
0!
00
1<
1;
09
14
13
1a
1`
1i
1h
0f
#155000
1!
b1 /
b1000110010001010101010001000011010010000010000000100000 .
10
b10 ^
1\
1I
0-
1,
#160000
0!
00
#165000
1!
b10 /
b1000101010110000100010101000011010101010101010001000101 .
10
b11 ^
b111 Z
1[
1]
b110 X
1>
1=
1J
1H
1G
1F
0D
1-
b1100 r
0~
1"!
1#!
1|
1{
1z
1y
1}
1n
1m
b111 r
1w
10!
1-!
1*!
1'!
1p
1o
0m
0w
1)!
1v
1u
1t
1$!
0v
1,!
1%!
0u
1/!
1&!
0t
12!
1x
#170000
0!
00
#175000
1!
b11 /
b1010011010101000100111101010010010001010010000000100000 .
10
b1 ^
0[
0\
0]
b111 k
1R
1Q
1P
0J
0I
0H
0,
1'
1&
1%
#180000
b10000011000 #
0!
00
0<
0;
0:
19
04
03
12
0a
0`
1_
0i
0h
0g
1f
#185000
1!
b1 /
b1000110010001010101010001000011010010000010000000100000 .
10
b10 ^
1\
1I
0-
1,
#190000
0!
00
#195000
1!
b10 /
b1000101010110000100010101000011010101010101010001000101 .
10
b11 ^
b1000 Z
1[
1]
b100 X
b111 3!
1N
1M
1L
0>
1J
1H
0G
0F
0E
1D
1-
b0 r
1~
0|
0{
0z
0}
0-!
1.!
0*!
1+!
0'!
1(!
1+
1*
1)
0p
0o
0n
1v
0,!
1u
0/!
0)!
1-!
0.!
1*!
0+!
1'!
0(!
1w
0v
1,!
0u
1/!
0$!
0&!
0%!
1u
0/!
1t
02!
1v
0,!
1&!
1%!
0u
1/!
0t
12!
0%!
0x
0&!
1t
02!
1u
0/!
1x
1&!
0t
12!
0&!
0x
1t
02!
1x
0x
#200000
0!
00
